{
	"_version": "1.1.0",
	"resources": [
		{
			"name": ".theming",
			"size": 93,
			"theme": "sap_belize_hcb"
		},
		{
			"name": "Notification.less",
			"size": 10072,
			"designtime": true,
			"theme": "sap_belize_hcb"
		},
		{
			"name": "css_variables.css",
			"size": 120,
			"theme": "sap_belize_hcb"
		},
		{
			"name": "css_variables.less",
			"size": 83626,
			"designtime": true,
			"theme": "sap_belize_hcb"
		},
		{
			"name": "css_variables.source.less",
			"size": 83258,
			"designtime": true,
			"theme": "sap_belize_hcb"
		},
		{
			"name": "library-RTL.css",
			"size": 5949,
			"theme": "sap_belize_hcb"
		},
		{
			"name": "library-parameters.json",
			"size": 2,
			"theme": "sap_belize_hcb"
		},
		{
			"name": "library.css",
			"size": 5945,
			"theme": "sap_belize_hcb"
		},
		{
			"name": "library.less",
			"size": 10609,
			"designtime": true,
			"theme": "sap_belize_hcb"
		},
		{
			"name": "library.source.less",
			"size": 315,
			"designtime": true,
			"theme": "sap_belize_hcb"
		},
		{
			"name": "library_skeleton-RTL.css",
			"size": 6552,
			"theme": "sap_belize_hcb"
		},
		{
			"name": "library_skeleton.css",
			"size": 6548,
			"theme": "sap_belize_hcb"
		}
	]
}