{
	"_version": "1.1.0",
	"resources": [
		{
			"name": ".theming",
			"size": 128,
			"theme": "sap_hcb"
		},
		{
			"name": "ContainerBase.less",
			"size": 172,
			"designtime": true,
			"theme": "sap_hcb"
		},
		{
			"name": "ListPanelStack.less",
			"size": 212,
			"designtime": true,
			"theme": "sap_hcb"
		},
		{
			"name": "MapContainer.less",
			"size": 177,
			"designtime": true,
			"theme": "sap_hcb"
		},
		{
			"name": "css_variables.css",
			"size": 157,
			"theme": "sap_hcb"
		},
		{
			"name": "css_variables.less",
			"size": 72801,
			"designtime": true,
			"theme": "sap_hcb"
		},
		{
			"name": "css_variables.source.less",
			"size": 72501,
			"designtime": true,
			"theme": "sap_hcb"
		},
		{
			"name": "library-RTL.css",
			"size": 43773,
			"theme": "sap_hcb"
		},
		{
			"name": "library-parameters.json",
			"size": 2,
			"theme": "sap_hcb"
		},
		{
			"name": "library.css",
			"size": 43763,
			"theme": "sap_hcb"
		},
		{
			"name": "library.less",
			"size": 1091,
			"designtime": true,
			"theme": "sap_hcb"
		},
		{
			"name": "library.source.less",
			"size": 319,
			"designtime": true,
			"theme": "sap_hcb"
		},
		{
			"name": "library_skeleton-RTL.css",
			"size": 44139,
			"theme": "sap_hcb"
		},
		{
			"name": "library_skeleton.css",
			"size": 44129,
			"theme": "sap_hcb"
		}
	]
}