{
	"_version": "1.1.0",
	"resources": [
		{
			"name": ".theming",
			"size": 93,
			"theme": "sap_belize_hcw"
		},
		{
			"name": "css_variables.css",
			"size": 125,
			"theme": "sap_belize_hcw"
		},
		{
			"name": "css_variables.less",
			"size": 83598,
			"designtime": true,
			"theme": "sap_belize_hcw"
		},
		{
			"name": "css_variables.source.less",
			"size": 83224,
			"designtime": true,
			"theme": "sap_belize_hcw"
		},
		{
			"name": "library-RTL.css",
			"size": 3062,
			"theme": "sap_belize_hcw"
		},
		{
			"name": "library-parameters.json",
			"size": 2,
			"theme": "sap_belize_hcw"
		},
		{
			"name": "library.css",
			"size": 3067,
			"theme": "sap_belize_hcw"
		},
		{
			"name": "library.less",
			"size": 450,
			"designtime": true,
			"theme": "sap_belize_hcw"
		},
		{
			"name": "library.source.less",
			"size": 260,
			"designtime": true,
			"theme": "sap_belize_hcw"
		},
		{
			"name": "library_skeleton-RTL.css",
			"size": 3348,
			"theme": "sap_belize_hcw"
		},
		{
			"name": "library_skeleton.css",
			"size": 3353,
			"theme": "sap_belize_hcw"
		}
	]
}