{
	"_version": "1.1.0",
	"resources": [
		{
			"name": ".theming",
			"size": 90,
			"theme": "sap_fiori_3"
		},
		{
			"name": "Inbox.less",
			"size": 2096,
			"designtime": true,
			"theme": "sap_fiori_3"
		},
		{
			"name": "SubstitutionRulesManager.less",
			"size": 540,
			"designtime": true,
			"theme": "sap_fiori_3"
		},
		{
			"name": "css_variables.css",
			"size": 119,
			"theme": "sap_fiori_3"
		},
		{
			"name": "css_variables.less",
			"size": 86053,
			"designtime": true,
			"theme": "sap_fiori_3"
		},
		{
			"name": "css_variables.source.less",
			"size": 85685,
			"designtime": true,
			"theme": "sap_fiori_3"
		},
		{
			"name": "library-RTL.css",
			"size": 17249,
			"theme": "sap_fiori_3"
		},
		{
			"name": "library-parameters.json",
			"size": 2,
			"theme": "sap_fiori_3"
		},
		{
			"name": "library.css",
			"size": 17248,
			"theme": "sap_fiori_3"
		},
		{
			"name": "library.less",
			"size": 3209,
			"designtime": true,
			"theme": "sap_fiori_3"
		},
		{
			"name": "library.source.less",
			"size": 311,
			"designtime": true,
			"theme": "sap_fiori_3"
		},
		{
			"name": "library_skeleton-RTL.css",
			"size": 17813,
			"theme": "sap_fiori_3"
		},
		{
			"name": "library_skeleton.css",
			"size": 17812,
			"theme": "sap_fiori_3"
		}
	]
}